rimac_analytics/__init__.py
rimac_analytics/common/__init__.py
rimac_analytics/common/core.py
rimac_analytics/constants/__init__.py
rimac_analytics/constants/constants.py
rimac_analytics/decorators/__init__.py
rimac_analytics/decorators/decorators.py
rimac_analytics/utils/__init__.py
rimac_analytics/utils/dataframe_utils.py
rimac_analytics/utils/format_utils.py
rimac_analytics-0.5.2.dist-info/DESCRIPTION.rst
rimac_analytics-0.5.2.dist-info/METADATA
rimac_analytics-0.5.2.dist-info/RECORD
rimac_analytics-0.5.2.dist-info/WHEEL
rimac_analytics-0.5.2.dist-info/metadata.json
rimac_analytics-0.5.2.dist-info/top_level.txt
