Metadata-Version: 2.0
Name: rimac-analytics
Version: 0.5.2
Summary: Rimac Analytics API
Home-page: https://bitbucket.org/rimac-analytics/rimac-analytics-api
Author: Diego y Ricardito
Author-email: ddce.2005@gmail.com
License: MIT
Platform: UNKNOWN
Requires-Python: >=3
